actinia/__init__.py
actinia/actinia.py
actinia/job.py
actinia/location.py
actinia/mapset.py
actinia/raster.py
actinia/region.py
actinia/strds.py
actinia/utils.py
actinia/vector.py
actinia/resources/__init__.py
actinia/resources/logger.py
actinia/resources/templating.py
actinia/templates/create_location.json
actinia_python_client-0.4.1.dist-info/LICENSE
actinia_python_client-0.4.1.dist-info/METADATA
actinia_python_client-0.4.1.dist-info/WHEEL
actinia_python_client-0.4.1.dist-info/top_level.txt
actinia_python_client-0.4.1.dist-info/RECORD
