Metadata-Version: 2.1
Name: actinia-python-client
Version: 0.4.1
Summary: Python client library for actinia requests.
Author-email: Anika Weinmann <weinmann@mundialis.de>
Maintainer-email: "mundialis GmbH & Co. KG" <info@mundialis.de>
Project-URL: Homepage, https://github.com/actinia-org/actinia-python-client
Project-URL: Bug Tracker, https://github.com/actinia-org/actinia-python-client/issues
Classifier: Programming Language :: Python :: 3
Classifier: License :: OSI Approved :: GNU General Public License v3 (GPLv3)
Classifier: Operating System :: OS Independent
Requires-Python: >=3.8
License-File: LICENSE
Requires-Dist: jinja2
Requires-Dist: requests
Requires-Dist: sphinx-material
